cdantic/__init__.py
cdantic/core.py
cdantic/types.py
cdantic-0.1.9.dist-info/METADATA
cdantic-0.1.9.dist-info/WHEEL
cdantic-0.1.9.dist-info/top_level.txt
cdantic-0.1.9.dist-info/RECORD
