Metadata-Version: 2.4
Name: cdantic
Version: 0.1.9
Summary: Type-safe Ctypes bindings using Pydantic models.
Author-email: Pytron Team <dev@pytron.io>
License: MIT
Project-URL: Homepage, https://github.com/pytron-org/cdantic
Classifier: Programming Language :: Python :: 3
Classifier: License :: OSI Approved :: MIT License
Classifier: Topic :: Software Development :: Libraries :: Python Modules
Requires-Python: >=3.8
Requires-Dist: pydantic>=2.0.0
